underlying_prompts/__init__.py
underlying_prompts/server.py
underlying_prompts-0.1.1.dist-info/LICENSE
underlying_prompts-0.1.1.dist-info/METADATA
underlying_prompts-0.1.1.dist-info/WHEEL
underlying_prompts-0.1.1.dist-info/entry_points.txt
underlying_prompts-0.1.1.dist-info/top_level.txt
underlying_prompts-0.1.1.dist-info/RECORD
