Metadata-Version: 2.1
Name: underlying-prompts
Version: 0.1.1
Summary: UNKNOWN
Home-page: https://github.com/tobegit3hub/underlying-prompts
Author: tobe
Author-email: tobeg3oogle@gmail.com
License: UNKNOWN
Platform: UNKNOWN
License-File: LICENSE
Requires-Dist: requests
Requires-Dist: flask
